{
	"records": [
		{
			"chartseq": "10100",
			"chart_code": "MIN",
			"chart_name": "TAKEOFF MINIMUMS",
			"pdf_name": "NC2TO.PDF"
		},
		{
			"chartseq": "10200",
			"chart_code": "MIN",
			"chart_name": "ALTERNATE MINIMUMS",
			"pdf_name": "NC2ALT.PDF"
		},
		{
			"chartseq": "50750",
			"chart_code": "IAP",
			"chart_name": "ILS OR LOC RWY 34",
			"pdf_name": "05440IL34.PDF"
		},
		{
			"chartseq": "53525",
			"chart_code": "IAP",
			"chart_name": "RNAV (GPS) RWY 04",
			"pdf_name": "05440R4.PDF"
		},
		{
			"chartseq": "53525",
			"chart_code": "IAP",
			"chart_name": "RNAV (GPS) RWY 16",
			"pdf_name": "05440R16.PDF"
		},
		{
			"chartseq": "53525",
			"chart_code": "IAP",
			"chart_name": "RNAV (GPS) RWY 22",
			"pdf_name": "05440R22.PDF"
		},
		{
			"chartseq": "53525",
			"chart_code": "IAP",
			"chart_name": "RNAV (GPS) RWY 34",
			"pdf_name": "05440R34.PDF"
		},
		{
			"chartseq": "55125",
			"chart_code": "IAP",
			"chart_name": "VOR/DME RWY 16",
			"pdf_name": "05440VD16.PDF"
		},
		{
			"chartseq": "55125",
			"chart_code": "IAP",
			"chart_name": "VOR/DME RWY 34",
			"pdf_name": "05440VD34.PDF"
		},
		{
			"chartseq": "55800",
			"chart_code": "IAP",
			"chart_name": "VOR RWY 16",
			"pdf_name": "05440V16.PDF"
		},
		{
			"chartseq": "55800",
			"chart_code": "IAP",
			"chart_name": "VOR RWY 34",
			"pdf_name": "05440V34.PDF"
		},
		{
			"chartseq": "70000",
			"chart_code": "APD",
			"chart_name": "AIRPORT DIAGRAM",
			"pdf_name": "05440AD.PDF"
		}
	],
	"meta": {
		"state_code": "KS",
		"state_fullname": "Kansas",
		"city_name": "HAYS",
		"airport_name": "HAYS RGNL",
		"military": "N",
		"apt_ident": "HYS",
		"icao_ident": "KHYS",
		"alnum": "5440",
		"cycle": "1702",
		"from_edate": "0901Z  02/02/17",
		"to_edate": "0901Z  03/02/17"
	}
}