{
	"records": [
		{
			"chartseq": "10100",
			"chart_code": "MIN",
			"chart_name": "TAKEOFF MINIMUMS",
			"pdf_name": "SC4TO.PDF"
		},
		{
			"chartseq": "10200",
			"chart_code": "MIN",
			"chart_name": "ALTERNATE MINIMUMS",
			"pdf_name": "SC4ALT.PDF"
		},
		{
			"chartseq": "10400",
			"chart_code": "MIN",
			"chart_name": "RADAR MINIMUMS",
			"pdf_name": "SC4RAD.PDF"
		},
		{
			"chartseq": "50750",
			"chart_code": "IAP",
			"chart_name": "ILS OR LOC RWY 13",
			"pdf_name": "00040IL13.PDF"
		},
		{
			"chartseq": "50750",
			"chart_code": "IAP",
			"chart_name": "ILS OR LOC/DME RWY 22R",
			"pdf_name": "00040ILD22R.PDF"
		},
		{
			"chartseq": "51200",
			"chart_code": "IAP",
			"chart_name": "ILS RWY 22R (SA CAT I - II)",
			"pdf_name": "00040I22RSAC1_2.PDF"
		},
		{
			"chartseq": "53525",
			"chart_code": "IAP",
			"chart_name": "RNAV (GPS) RWY 04L",
			"pdf_name": "00040R4L.PDF"
		},
		{
			"chartseq": "53525",
			"chart_code": "IAP",
			"chart_name": "RNAV (GPS) RWY 13",
			"pdf_name": "00040R13.PDF"
		},
		{
			"chartseq": "53525",
			"chart_code": "IAP",
			"chart_name": "RNAV (GPS) RWY 22R",
			"pdf_name": "00040R22R.PDF"
		},
		{
			"chartseq": "53525",
			"chart_code": "IAP",
			"chart_name": "RNAV (GPS) RWY 31",
			"pdf_name": "00040R31.PDF"
		},
		{
			"chartseq": "55800",
			"chart_code": "IAP",
			"chart_name": "VOR RWY 04L",
			"pdf_name": "00040V4L.PDF"
		},
		{
			"chartseq": "70000",
			"chart_code": "APD",
			"chart_name": "AIRPORT DIAGRAM",
			"pdf_name": "00040AD.PDF"
		}
	],
	"meta": {
		"state_code": "LA",
		"state_fullname": "Louisiana",
		"city_name": "BATON ROUGE",
		"airport_name": "BATON ROUGE METROPOLITAN, RYAN FIELD",
		"military": "N",
		"apt_ident": "BTR",
		"icao_ident": "KBTR",
		"alnum": "40",
		"cycle": "1702",
		"from_edate": "0901Z  02/02/17",
		"to_edate": "0901Z  03/02/17"
	}
}