{
	"records": [
		{
			"chartseq": "10100",
			"chart_code": "MIN",
			"chart_name": "TAKEOFF MINIMUMS",
			"pdf_name": "AKTO.PDF"
		},
		{
			"chartseq": "10200",
			"chart_code": "MIN",
			"chart_name": "ALTERNATE MINIMUMS",
			"pdf_name": "AKALT.PDF"
		},
		{
			"chartseq": "53525",
			"chart_code": "IAP",
			"chart_name": "RNAV (GPS) RWY 04",
			"pdf_name": "09207R4.PDF"
		},
		{
			"chartseq": "53525",
			"chart_code": "IAP",
			"chart_name": "RNAV (GPS) RWY 27",
			"pdf_name": "09207R27.PDF"
		},
		{
			"chartseq": "53525",
			"chart_code": "IAP",
			"chart_name": "RNAV (GPS) Y RWY 22",
			"pdf_name": "09207RY22.PDF"
		},
		{
			"chartseq": "53525",
			"chart_code": "IAP",
			"chart_name": "RNAV (GPS) Z RWY 22",
			"pdf_name": "09207RZ22.PDF"
		},
		{
			"chartseq": "55800",
			"chart_code": "IAP",
			"chart_name": "VOR RWY 04",
			"pdf_name": "09207V4.PDF"
		},
		{
			"chartseq": "55800",
			"chart_code": "IAP",
			"chart_name": "VOR RWY 22",
			"pdf_name": "09207V22.PDF"
		}
	],
	"meta": {
		"state_code": "AK",
		"state_fullname": "Alaska",
		"city_name": "SELAWIK",
		"airport_name": "SELAWIK",
		"military": "N",
		"apt_ident": "WLK",
		"icao_ident": "PASK",
		"alnum": "9207",
		"cycle": "1702",
		"from_edate": "0901Z  02/02/17",
		"to_edate": "0901Z  03/02/17"
	}
}