{
	"records": [
		{
			"chartseq": "10100",
			"chart_code": "MIN",
			"chart_name": "TAKEOFF MINIMUMS",
			"pdf_name": "EC1TO.PDF"
		},
		{
			"chartseq": "10200",
			"chart_code": "MIN",
			"chart_name": "ALTERNATE MINIMUMS",
			"pdf_name": "EC1ALT.PDF"
		},
		{
			"chartseq": "50750",
			"chart_code": "IAP",
			"chart_name": "ILS OR LOC/DME RWY 27",
			"pdf_name": "06474ILD27.PDF"
		},
		{
			"chartseq": "53525",
			"chart_code": "IAP",
			"chart_name": "RNAV (GPS) RWY 09",
			"pdf_name": "06474R9.PDF"
		},
		{
			"chartseq": "53525",
			"chart_code": "IAP",
			"chart_name": "RNAV (GPS) RWY 27",
			"pdf_name": "06474R27.PDF"
		},
		{
			"chartseq": "55125",
			"chart_code": "IAP",
			"chart_name": "VOR/DME-A",
			"pdf_name": "06474VDA.PDF"
		}
	],
	"meta": {
		"state_code": "MI",
		"state_fullname": "Michigan",
		"city_name": "SAGINAW",
		"airport_name": "SAGINAW COUNTY H W BROWNE",
		"military": "N",
		"apt_ident": "HYX",
		"icao_ident": "KHYX",
		"alnum": "6474"
	}
}