{
	"records": [
		{
			"chartseq": "10100",
			"chart_code": "MIN",
			"chart_name": "TAKEOFF MINIMUMS",
			"pdf_name": "SE1TO.PDF"
		},
		{
			"chartseq": "10400",
			"chart_code": "MIN",
			"chart_name": "RADAR MINIMUMS",
			"pdf_name": "SE1RAD.PDF"
		},
		{
			"chartseq": "50750",
			"chart_code": "IAP",
			"chart_name": "ILS OR LOC RWY 23",
			"pdf_name": "00679IL23.PDF"
		},
		{
			"chartseq": "53525",
			"chart_code": "IAP",
			"chart_name": "RNAV (GPS) RWY 18",
			"pdf_name": "00679R18.PDF"
		},
		{
			"chartseq": "53525",
			"chart_code": "IAP",
			"chart_name": "RNAV (GPS) RWY 23",
			"pdf_name": "00679R23.PDF"
		},
		{
			"chartseq": "57500",
			"chart_code": "IAP",
			"chart_name": "NDB RWY 23",
			"pdf_name": "00679N23.PDF"
		},
		{
			"chartseq": "70000",
			"chart_code": "APD",
			"chart_name": "AIRPORT DIAGRAM",
			"pdf_name": "00679AD.PDF"
		}
	],
	"meta": {
		"state_code": "KY",
		"state_fullname": "Kentucky",
		"city_name": "FORT CAMPBELL",
		"airport_name": "CAMPBELL AAF",
		"military": "M",
		"apt_ident": "HOP",
		"icao_ident": "KHOP",
		"alnum": "679"
	}
}