{
	"records": [
		{
			"chartseq": "10100",
			"chart_code": "MIN",
			"chart_name": "TAKEOFF MINIMUMS",
			"pdf_name": "SC4TO.PDF"
		},
		{
			"chartseq": "10200",
			"chart_code": "MIN",
			"chart_name": "ALTERNATE MINIMUMS",
			"pdf_name": "SC4ALT.PDF"
		},
		{
			"chartseq": "53525",
			"chart_code": "IAP",
			"chart_name": "RNAV (GPS) RWY 18",
			"pdf_name": "06960R18.PDF"
		},
		{
			"chartseq": "53525",
			"chart_code": "IAP",
			"chart_name": "RNAV (GPS) RWY 36",
			"pdf_name": "06960R36.PDF"
		}
	],
	"meta": {
		"state_code": "MS",
		"state_fullname": "Mississippi",
		"city_name": "PHILADELPHIA",
		"airport_name": "PHILADELPHIA MUNI",
		"military": "N",
		"apt_ident": "MPE",
		"icao_ident": "KMPE",
		"alnum": "6960"
	}
}