{
	"records": [
		{
			"chartseq": "10100",
			"chart_code": "MIN",
			"chart_name": "TAKEOFF MINIMUMS",
			"pdf_name": "NC2TO.PDF"
		},
		{
			"chartseq": "10200",
			"chart_code": "MIN",
			"chart_name": "ALTERNATE MINIMUMS",
			"pdf_name": "NC2ALT.PDF"
		},
		{
			"chartseq": "53525",
			"chart_code": "IAP",
			"chart_name": "RNAV (GPS) RWY 10",
			"pdf_name": "06680R10.PDF"
		},
		{
			"chartseq": "53525",
			"chart_code": "IAP",
			"chart_name": "RNAV (GPS) RWY 28",
			"pdf_name": "06680R28.PDF"
		}
	],
	"meta": {
		"state_code": "NE",
		"state_fullname": "Nebraska",
		"city_name": "KIMBALL",
		"airport_name": "KIMBALL MUNI/ROBERT E ARRAJ FIELD",
		"military": "N",
		"apt_ident": "IBM",
		"icao_ident": "KIBM",
		"alnum": "6680"
	}
}