{
	"records": [
		{
			"chartseq": "10100",
			"chart_code": "MIN",
			"chart_name": "TAKEOFF MINIMUMS",
			"pdf_name": "EC2TO.PDF"
		},
		{
			"chartseq": "10200",
			"chart_code": "MIN",
			"chart_name": "ALTERNATE MINIMUMS",
			"pdf_name": "EC2ALT.PDF"
		},
		{
			"chartseq": "53525",
			"chart_code": "IAP",
			"chart_name": "RNAV (GPS) RWY 14",
			"pdf_name": "05554R14.PDF"
		},
		{
			"chartseq": "55800",
			"chart_code": "IAP",
			"chart_name": "VOR-A",
			"pdf_name": "05554VA.PDF"
		}
	],
	"meta": {
		"state_code": "OH",
		"state_fullname": "Ohio",
		"city_name": "NEW PHILADELPHIA",
		"airport_name": "HARRY CLEVER FIELD",
		"military": "N",
		"apt_ident": "PHD",
		"icao_ident": "KPHD",
		"alnum": "5554"
	}
}